mrkdwn2html/__init__.py
mrkdwn2html/mrkdwn2html.py
mrkdwn2html-0.0.4.dist-info/LICENSE
mrkdwn2html-0.0.4.dist-info/METADATA
mrkdwn2html-0.0.4.dist-info/WHEEL
mrkdwn2html-0.0.4.dist-info/top_level.txt
mrkdwn2html-0.0.4.dist-info/RECORD
